MetaboDistTrees/__init__.py
MetaboDistTrees/metabodisttrees.py
MetaboDistTrees/data/ChemOnt_2_1.obo
MetaboDistTrees/test/test.py
MetaboDistTrees-0.1.3.dist-info/LICENSE
MetaboDistTrees-0.1.3.dist-info/METADATA
MetaboDistTrees-0.1.3.dist-info/WHEEL
MetaboDistTrees-0.1.3.dist-info/top_level.txt
MetaboDistTrees-0.1.3.dist-info/RECORD
