Metadata-Version: 2.1
Name: MetaboDistTrees
Version: 0.1.3
Summary: A python implementation for building chemically informed distance trees
Home-page: https://github.com/madeleineernst/MetaboDistTrees
Author: Madeleine Ernst
Author-email: mernst@ucsd.edu
License: UNKNOWN
Platform: UNKNOWN
Classifier: Programming Language :: Python :: 3
Classifier: License :: OSI Approved :: MIT License
Classifier: Operating System :: OS Independent
Requires-Dist: scipy
Requires-Dist: numpy
Requires-Dist: pandas
Requires-Dist: obonet
Requires-Dist: networkx
